{"server_type": "forge", "server_version": "1.20.1", "version_jdk": "17", "gbs_de_ram_a_usar": 4, "servicio_a_usar": "playit", "actualizaciones_discord": true, "webhook_de_discord": "https://discord.com/api/webhooks/1465526483328962563/6R2V3dhr3wUzEqHuvWM5tKhfA792i8_uX9rYUfjpuZ5hKe_qF1uO_1tNm5nnfhJijVSS", "iniciando_servidor": true, "decir_ip": true, "usar_dropbox": false, "token_dropbox": "", "debug_mode": false, "flags": "-Xms2G -Xmx4G", "zerotier_network": "", "backup_mode": "luna", "backup_auto": true, "online-mode": false, "donotaskupdate": true, "billing_activado": true, "auto_apagar": true}